{
  "tasks": [
    {
      "status": 1,
      "task_name": "asfdsadfsdfsadfasdfasfd asdfasdf asdf this is sujanasdf asdfasdf thisdfasdfsadfasdfasdf asdfasdfasdf asdfsadfasdfasdfsafdasfasfdasfdasdfasfdkjhkj khk",
      "is_important": true,
      "id": 3
    },
    {
      "task_name": "asdfsadfdsdf htersadfasdfsadfsasdfasfd asdfasdf adfsadfsdfsdfsdfsadfasdf",
      "status": 1,
      "is_important": false,
      "id": 4
    },
    {
      "status": 1,
      "task_name": "asdfsadfdf asdfasdf thasdfjasdf asdhfkasdfkaskdfhkasjfdlkjalksfdjlkajsdf asdlfkjalksdjflkasdf aslkdfjlaksdjflkasdfjl sadlkfjlaksdjflkasdf aslkdfjalskdfjasdf askdfhlasdf",
      "id": 5
    },
    {
      "task_name": "asdfasdffff",
      "status": 1,
      "id": 6
    },
    {
      "status": 1,
      "task_name": "asdfasdf",
      "is_important": false,
      "id": 7
    },
    {
      "status": 1,
      "task_name": "asdf",
      "is_important": false,
      "id": 8
    },
    {
      "task_name": "asdfasdf",
      "status": 1,
      "isImportant": false,
      "id": 9
    },
    {
      "status": 1,
      "task_name": "asdfsadf",
      "is_important": false,
      "id": 10
    },
    {
      "status": 1,
      "task_name": "asdf",
      "is_important": false,
      "id": 11
    },
    {
      "task_name": "sujan",
      "status": 1,
      "isImportant": false,
      "id": 12
    },
    {
      "task_name": "Tasdfa",
      "status": 1,
      "isImportant": false,
      "id": 13
    }
  ]
}